braidvisualiser/__init__.py
braidvisualiser/braid.py
braidvisualiser-0.2.2.dist-info/LICENSE
braidvisualiser-0.2.2.dist-info/METADATA
braidvisualiser-0.2.2.dist-info/WHEEL
braidvisualiser-0.2.2.dist-info/RECORD
