Metadata-Version: 2.1
Name: braidvisualiser
Version: 0.2.2
Summary: Python library providing functionality for the creation and rendering of Artin braids.
License: MIT
Author: Rex Greenway
Requires-Python: >=3.10,<4.0
Classifier: License :: OSI Approved :: MIT License
Classifier: Programming Language :: Python :: 3
Classifier: Programming Language :: Python :: 3.10
Classifier: Programming Language :: Python :: 3.11
Classifier: Programming Language :: Python :: 3.12
Requires-Dist: matplotlib (>=3.8.2,<4.0.0)
Requires-Dist: numpy (>=1.26.3,<2.0.0)
